MANIFEST.in
README.rst
development.ini
setup.cfg
setup.py
tox.ini
docs/configuration.rst
docs/developer-manual.rst
docs/index.rst
docs/installation.rst
docs/tutorial.rst
kotti_mapreduce/__init__.py
kotti_mapreduce/resources.py
kotti_mapreduce/views.py
kotti_mapreduce.egg-info/PKG-INFO
kotti_mapreduce.egg-info/SOURCES.txt
kotti_mapreduce.egg-info/dependency_links.txt
kotti_mapreduce.egg-info/entry_points.txt
kotti_mapreduce.egg-info/not-zip-safe
kotti_mapreduce.egg-info/requires.txt
kotti_mapreduce.egg-info/top_level.txt
kotti_mapreduce/locale/kotti_mapreduce.pot
kotti_mapreduce/locale/ja/LC_MESSAGES/kotti_mapreduce.mo
kotti_mapreduce/locale/ja/LC_MESSAGES/kotti_mapreduce.po
kotti_mapreduce/static/bootstrap-edit.js
kotti_mapreduce/static/emrjobresource-view.js
kotti_mapreduce/static/jobflow-edit.js
kotti_mapreduce/static/jobflow-view.js
kotti_mapreduce/static/spinner.gif
kotti_mapreduce/static/spinner2.gif
kotti_mapreduce/static/style.css
kotti_mapreduce/templates/bootstrap-edit.pt
kotti_mapreduce/templates/bootstrap-view.pt
kotti_mapreduce/templates/emrjobresource-view.pt
kotti_mapreduce/templates/jobcontainer-view.pt
kotti_mapreduce/templates/jobflow-edit.pt
kotti_mapreduce/templates/jobflow-view.pt
kotti_mapreduce/templates/jobstep-view.pt
kotti_mapreduce/templates/movelink.pt
kotti_mapreduce/templates/deform/bootstrap-list.pt
kotti_mapreduce/tests/__init__.py
kotti_mapreduce/tests/browser.txt
kotti_mapreduce/util/__init__.py
kotti_mapreduce/util/datastore.py
kotti_mapreduce/util/helper.py
kotti_mapreduce/util/job.py
kotti_mapreduce/util/model.py