Metadata-Version: 1.1
Name: kotti-mapreduce
Version: 0.2.0
Summary: The MapReduce addon for Kotti sites
Home-page: https://github.com/t2y/kotti_mapreduce
Author: Tetsuya Morimoto
Author-email: tetsuya dot morimoto at gmail dot com
License: BSD-derived (http://www.repoze.org/LICENSE.txt)
Keywords: kotti web emr mapreduce
Platform: UNKNOWN
Classifier: Development Status :: 3 - Alpha
Classifier: Programming Language :: Python
Classifier: Framework :: Pylons
Classifier: Topic :: Internet :: WWW/HTTP
Classifier: Topic :: Internet :: WWW/HTTP :: Dynamic Content
Classifier: Topic :: Internet :: WWW/HTTP :: WSGI :: Application
Classifier: License :: Repoze Public License
